robosignatory/__init__.py
robosignatory/atomic.py
robosignatory/cli.py
robosignatory/consumer.py
robosignatory/coreos.py
robosignatory/tag.py
robosignatory/utils.py
robosignatory/work.py
robosignatory/xml.py
robosignatory-0.8.2.dist-info/LICENSE
robosignatory-0.8.2.dist-info/METADATA
robosignatory-0.8.2.dist-info/WHEEL
robosignatory-0.8.2.dist-info/entry_points.txt
robosignatory-0.8.2.dist-info/top_level.txt
robosignatory-0.8.2.dist-info/RECORD
